{
  "_class": "shapePath",
  "booleanOperation": -1,
  "do_objectID": "063B1A3B-BDEF-4804-9602-50ED30E101BA",
  "edited": true,
  "exportOptions": {
    "_class": "exportOptions",
    "do_objectID": "6BE0649F-A786-44B2-BE65-8707574319ED",
    "exportFormats": [
    ],
    "includedLayerIds": [
    ],
    "layerOptions": 0,
    "shouldTrim": false
  },
  "frame": {
    "_class": "rect",
    "constrainProportions": false,
    "do_objectID": "90C1DD84-AE7C-48EF-B1A5-D175F25997F6",
    "height": 0.4856484797728626,
    "width": 0.4856484797729408,
    "x": 33.92226231506512,
    "y": 16.36641832145789
  },
  "isClosed": true,
  "isFixedToViewport": false,
  "isFlippedHorizontal": false,
  "isFlippedVertical": false,
  "isLocked": false,
  "isVisible": true,
  "layerListExpandedType": 0,
  "name": "Path",
  "nameIsFixed": false,
  "pointRadiusBehaviour": 1,
  "points": [
    {
      "_class": "curvePoint",
      "cornerRadius": 0,
      "curveFrom": "{0.048000000000001819, 0.095999999999996533}",
      "curveMode": 4,
      "curveTo": "{0, 0.14399999999999835}",
      "hasCurveFrom": true,
      "hasCurveTo": false,
      "point": "{0, 0.14399999999999835}"
    },
    {
      "_class": "curvePoint",
      "cornerRadius": 0,
      "curveFrom": "{0, 0}",
      "curveMode": 4,
      "curveTo": "{0.096000000000003638, 0.047999999999994714}",
      "hasCurveFrom": false,
      "hasCurveTo": true,
      "point": "{0, 0}"
    }
  ],
  "resizingConstraint": 63,
  "resizingType": 0,
  "rotation": 0,
  "shouldBreakMaskChain": false
}