{
  "_class": "shapePath",
  "booleanOperation": -1,
  "do_objectID": "3C3461E0-A6AE-4594-8E0E-72FBA0F7F065",
  "edited": true,
  "exportOptions": {
    "_class": "exportOptions",
    "do_objectID": "B23864B7-B86A-4138-B0EE-61444DA17BD5",
    "exportFormats": [
    ],
    "includedLayerIds": [
    ],
    "layerOptions": 0,
    "shouldTrim": false
  },
  "frame": {
    "_class": "rect",
    "constrainProportions": false,
    "do_objectID": "95270732-4148-4130-BD03-9679C98D2A59",
    "height": 0.4856484797728734,
    "width": 0.4856484797729053,
    "x": 69.60576996854176,
    "y": 0.07485441899706892
  },
  "isClosed": true,
  "isFixedToViewport": false,
  "isFlippedHorizontal": false,
  "isFlippedVertical": false,
  "isLocked": false,
  "isVisible": true,
  "layerListExpandedType": 0,
  "name": "Path",
  "nameIsFixed": false,
  "pointRadiusBehaviour": 1,
  "points": [
    {
      "_class": "curvePoint",
      "cornerRadius": 0,
      "curveFrom": "{0.132000000000005, 0.030000000000001137}",
      "curveMode": 4,
      "curveTo": "{0.14400000000000546, 0}",
      "hasCurveFrom": true,
      "hasCurveTo": false,
      "point": "{0.14400000000000546, 0}"
    },
    {
      "_class": "curvePoint",
      "cornerRadius": 0,
      "curveFrom": "{0.036000000000001364, 0.090000000000003411}",
      "curveMode": 4,
      "curveTo": "{0.10800000000000409, 0.066000000000002501}",
      "hasCurveFrom": true,
      "hasCurveTo": true,
      "point": "{0.10800000000000409, 0.090000000000003411}"
    },
    {
      "_class": "curvePoint",
      "cornerRadius": 0,
      "curveFrom": "{0, 0.018000000000000682}",
      "curveMode": 4,
      "curveTo": "{0, 0.054000000000002046}",
      "hasCurveFrom": false,
      "hasCurveTo": true,
      "point": "{0, 0.018000000000000682}"
    }
  ],
  "resizingConstraint": 63,
  "resizingType": 0,
  "rotation": 0,
  "shouldBreakMaskChain": false
}